{
  "vegetation_percentage": 33.89042317949302,
  "high_density_percentage": 20.018791105543375,
  "medium_density_percentage": 9.008152302859475,
  "low_density_percentage": 4.8634797710901685,
  "ndvi_mean": 0.5586007833480835,
  "total_pixels": 526845,
  "vegetation_pixels": 178550,
  "images_processed": 1,
  "images_found": 1,
  "ndvi_threshold": 0.3,
  "geographic_bounds": {
    "west": -2.324467,
    "south": 53.324303,
    "east": -2.099247,
    "north": 53.554986,
    "crs": "EPSG:4326"
  },
  "city_info": {
    "name": "Manchester, United Kingdom",
    "center_lat": 53.4396445,
    "center_lon": -2.211857
  },
  "processing_config": {
    "ndvi_threshold": 0.3,
    "cloud_threshold": 20,
    "highlight_alpha": 0.6,
    "date_range": "2020-05 to 2020-05"
  },
  "baseline_vegetation_2020": null,
  "percent_change_vs_2020": null,
  "cloud_excluded_percentage": 58.09868177547476,
  "output_files": [
    "vegetation_highlighted.png",
    "ndvi_visualization.png",
    "false_color_base.png"
  ]
}